ridgeplot/__init__.py
ridgeplot/_figure_factory.py
ridgeplot/_hist.py
ridgeplot/_kde.py
ridgeplot/_missing.py
ridgeplot/_ridgeplot.py
ridgeplot/_types.py
ridgeplot/_utils.py
ridgeplot/_version.py
ridgeplot/py.typed
ridgeplot/_color/__init__.py
ridgeplot/_color/colorscale.py
ridgeplot/_color/css_colors.py
ridgeplot/_color/interpolation.py
ridgeplot/_color/utils.py
ridgeplot/_obj/__init__.py
ridgeplot/_obj/traces/__init__.py
ridgeplot/_obj/traces/area.py
ridgeplot/_obj/traces/bar.py
ridgeplot/_obj/traces/base.py
ridgeplot/_vendor/__init__.py
ridgeplot/_vendor/_typeis.py
ridgeplot/datasets/__init__.py
ridgeplot/datasets/data/lincoln-weather.csv
ridgeplot/datasets/data/probly-illinois.csv
ridgeplot/datasets/data/probly-wadefagen.csv
ridgeplot/datasets/data/probly-zonination.csv
ridgeplot-0.5.0.dist-info/licenses/LICENSE
ridgeplot-0.5.0.dist-info/METADATA
ridgeplot-0.5.0.dist-info/WHEEL
ridgeplot-0.5.0.dist-info/top_level.txt
ridgeplot-0.5.0.dist-info/RECORD
