Metadata-Version: 2.4
Name: ridgeplot
Version: 0.5.0
Summary: Beautiful ridgeline plots in python
Author: Tomas Pereira de Vasconcelos
Maintainer-email: Tomas Pereira de Vasconcelos <tomasvasconcelos1@gmail.com>
License: The MIT License (MIT)
Project-URL: Homepage, https://github.com/tpvasconcelos/ridgeplot
Project-URL: Documentation, https://ridgeplot.readthedocs.io/en/stable/
Project-URL: Source code, https://github.com/tpvasconcelos/ridgeplot
Project-URL: Issue Tracker, https://github.com/tpvasconcelos/ridgeplot/issues
Project-URL: Changelog, https://ridgeplot.readthedocs.io/en/stable/reference/changelog.html
Keywords: ridgeline,ridgeplot,joyplot,ggridges,ridges,ridge,plot,plotting,distplot,plotly,data-visualization,visualization,data-science,statistics,ggplot
Classifier: Development Status :: 3 - Alpha
Classifier: Intended Audience :: Developers
Classifier: Intended Audience :: Science/Research
Classifier: License :: OSI Approved :: MIT License
Classifier: Natural Language :: English
Classifier: Programming Language :: Python :: 3
Classifier: Programming Language :: Python :: 3.10
Classifier: Programming Language :: Python :: 3.11
Classifier: Programming Language :: Python :: 3.12
Classifier: Programming Language :: Python :: 3.13
Classifier: Programming Language :: Python :: Implementation :: CPython
Classifier: Topic :: Software Development
Classifier: Topic :: Scientific/Engineering
Classifier: Topic :: Scientific/Engineering :: Information Analysis
Classifier: Topic :: Scientific/Engineering :: Visualization
Classifier: Typing :: Typed
Requires-Python: >=3.10
License-File: LICENSE
Requires-Dist: numpy>=1
Requires-Dist: plotly>=5.20
Requires-Dist: statsmodels!=0.14.2,>=0.12
Requires-Dist: typing-extensions
Dynamic: license-file
